a2c_smcp/__init__.py
a2c_smcp/agent/__init__.py
a2c_smcp/agent/auth.py
a2c_smcp/agent/base.py
a2c_smcp/agent/client.py
a2c_smcp/agent/sync_client.py
a2c_smcp/agent/types.py
a2c_smcp/computer/__init__.py
a2c_smcp/computer/base.py
a2c_smcp/computer/cli/__init__.py
a2c_smcp/computer/cli/interactive_impl.py
a2c_smcp/computer/cli/main.py
a2c_smcp/computer/cli/utils.py
a2c_smcp/computer/computer.py
a2c_smcp/computer/desktop/__init__.py
a2c_smcp/computer/desktop/organize.py
a2c_smcp/computer/inputs/__init__.py
a2c_smcp/computer/inputs/base.py
a2c_smcp/computer/inputs/cli_io.py
a2c_smcp/computer/inputs/render.py
a2c_smcp/computer/inputs/resolver.py
a2c_smcp/computer/mcp_clients/__init__.py
a2c_smcp/computer/mcp_clients/base_client.py
a2c_smcp/computer/mcp_clients/base_client.pyi
a2c_smcp/computer/mcp_clients/http_client.py
a2c_smcp/computer/mcp_clients/manager.py
a2c_smcp/computer/mcp_clients/model.py
a2c_smcp/computer/mcp_clients/sse_client.py
a2c_smcp/computer/mcp_clients/stdio_client.py
a2c_smcp/computer/mcp_clients/utils.py
a2c_smcp/computer/socketio/__init__.py
a2c_smcp/computer/socketio/client.py
a2c_smcp/computer/types.py
a2c_smcp/computer/utils/__init__.py
a2c_smcp/computer/utils/console.py
a2c_smcp/py.typed
a2c_smcp/server/__init__.py
a2c_smcp/server/auth.py
a2c_smcp/server/base.py
a2c_smcp/server/namespace.py
a2c_smcp/server/sync_auth.py
a2c_smcp/server/sync_base.py
a2c_smcp/server/sync_namespace.py
a2c_smcp/server/types.py
a2c_smcp/server/utils.py
a2c_smcp/smcp.py
a2c_smcp/types.py
a2c_smcp/utils/__init__.py
a2c_smcp/utils/async_property/__init__.py
a2c_smcp/utils/async_property/base.py
a2c_smcp/utils/async_property/proxy.py
a2c_smcp/utils/logger.py
a2c_smcp/utils/window_uri.py
a2c_smcp-0.1.1rc6.dist-info/METADATA
a2c_smcp-0.1.1rc6.dist-info/WHEEL
a2c_smcp-0.1.1rc6.dist-info/entry_points.txt
a2c_smcp-0.1.1rc6.dist-info/licenses/LICENSE
a2c_smcp-0.1.1rc6.dist-info/RECORD
